lb/nightly/utils/Repository.py
lb/nightly/utils/__init__.py
lb/nightly/utils/_deployment_helpers.py
lb_nightly_utils-0.4.1.dist-info/LICENSE
lb_nightly_utils-0.4.1.dist-info/WHEEL
lb_nightly_utils-0.4.1.dist-info/METADATA
lb_nightly_utils-0.4.1.dist-info/RECORD
